jasni/__init__.py
jasni/client.py
jasni/errors.py
jasni/http.py
jasni/py.typed
jasni/types.py
jasni/webhooks.py
jasni/resources/__init__.py
jasni/resources/accounts.py
jasni/resources/drafts.py
jasni/resources/emails.py
jasni/resources/labels.py
jasni/resources/webhooks.py
jasni_sdk-0.1.1.dist-info/METADATA
jasni_sdk-0.1.1.dist-info/WHEEL
jasni_sdk-0.1.1.dist-info/licenses/LICENSE
jasni_sdk-0.1.1.dist-info/RECORD
